.gitignore
.readthedocs.yml
LICENSE
README.rst
logo.png
requirements.txt
setup.py
.github/workflows/edit_version.py
.github/workflows/publish.yml
Stealthy_wavelink.egg-info/PKG-INFO
Stealthy_wavelink.egg-info/SOURCES.txt
Stealthy_wavelink.egg-info/dependency_links.txt
Stealthy_wavelink.egg-info/requires.txt
Stealthy_wavelink.egg-info/top_level.txt
docs/conf.py
docs/faq.rst
docs/index.rst
docs/installing.rst
docs/logo.png
docs/recipes.rst
docs/requirements_rtd.txt
docs/wavelink.rst
docs/_static/logo.png
docs/_static/wl_dark.png
docs/_static/css/custom.css
docs/extensions/attributetable.py
docs/exts/spotify.rst
examples/basic_cog.py
wavelink/__init__.py
wavelink/abc.py
wavelink/backoff.py
wavelink/enums.py
wavelink/errors.py
wavelink/player.py
wavelink/pool.py
wavelink/py.typed
wavelink/queue.py
wavelink/stats.py
wavelink/tracks.py
wavelink/utils.py
wavelink/websocket.py
wavelink/ext/spotify/__init__.py
wavelink/types/__init__.py
wavelink/types/queue.py