Metadata-Version: 2.1
Name: Stealthy-wavelink
Version: 1.1.1
Summary: A robust and powerful Lavalink wrapper for disnake and derivatives.
Home-page: https://github.com/realstealthninja/Stealthy-wavelink
Author: PythonistaGuild, EvieePy, stealthninja
License: MIT
Platform: UNKNOWN
Classifier: License :: OSI Approved :: MIT License
Classifier: Intended Audience :: Developers
Classifier: Natural Language :: English
Classifier: Operating System :: OS Independent
Classifier: Programming Language :: Python :: 3.8
Classifier: Programming Language :: Python :: 3.9
Classifier: Programming Language :: Python :: 3.10
Classifier: Topic :: Internet
Classifier: Topic :: Software Development :: Libraries
Classifier: Topic :: Software Development :: Libraries :: Python Modules
Classifier: Topic :: Utilities
License-File: LICENSE
